{
  "updated": "2026-04-04",
  "official_peg": 6.96,
  "series": [
    {
      "date": "2025-11-28",
      "mid": 10.391868,
      "spread_pct": 0.204108,
      "gap": 3.431868,
      "log_depth": 13.38945,
      "z_gap": 1.690339,
      "z_spread": 0.574907,
      "z_liq": -1.12807,
      "emp": 1.142978,
      "emp_rolling": null,
      "emp_dfm": 1.879991,
      "emp_dfm_lo": 1.774204,
      "emp_dfm_hi": 1.985778,
      "prob_depr_14d": 0.116174,
      "prob_depr_30d": 0.02092,
      "alarm_mass_14d": -0.071587,
      "alarm_mass_30d": -0.048518
    },
    {
      "date": "2025-11-29",
      "mid": 10.292927,
      "spread_pct": 0.157259,
      "gap": 3.332927,
      "log_depth": 13.592463,
      "z_gap": 1.470669,
      "z_spread": 0.523409,
      "z_liq": -0.704281,
      "emp": 1.09769,
      "emp_rolling": null,
      "emp_dfm": 1.608951,
      "emp_dfm_lo": 1.50346,
      "emp_dfm_hi": 1.714443,
      "prob_depr_14d": 0.146876,
      "prob_depr_30d": 0.031545,
      "alarm_mass_14d": -0.053937,
      "alarm_mass_30d": -0.044915
    },
    {
      "date": "2025-11-30",
      "mid": 10.144853,
      "spread_pct": 0.168836,
      "gap": 3.184853,
      "log_depth": 13.354282,
      "z_gap": 1.141912,
      "z_spread": 0.063542,
      "z_liq": -0.325112,
      "emp": 0.685344,
      "emp_rolling": null,
      "emp_dfm": 1.194353,
      "emp_dfm_lo": 1.088862,
      "emp_dfm_hi": 1.299845,
      "prob_depr_14d": 0.134695,
      "prob_depr_30d": 0.024309,
      "alarm_mass_14d": -0.096265,
      "alarm_mass_30d": -0.09735
    },
    {
      "date": "2025-12-01",
      "mid": 10.094195,
      "spread_pct": 0.182976,
      "gap": 3.134195,
      "log_depth": 13.279865,
      "z_gap": 1.02944,
      "z_spread": 0.556452,
      "z_liq": -1.275018,
      "emp": 0.653529,
      "emp_rolling": null,
      "emp_dfm": 1.055914,
      "emp_dfm_lo": 0.950422,
      "emp_dfm_hi": 1.161405,
      "prob_depr_14d": 0.252594,
      "prob_depr_30d": 0.113615,
      "alarm_mass_14d": 0.010383,
      "alarm_mass_30d": -0.022757
    },
    {
      "date": "2025-12-02",
      "mid": 9.806073,
      "spread_pct": 0.189742,
      "gap": 2.846073,
      "log_depth": 13.642497,
      "z_gap": 0.389748,
      "z_spread": 1.078519,
      "z_liq": -0.786502,
      "emp": 0.751061,
      "emp_rolling": null,
      "emp_dfm": 0.265813,
      "emp_dfm_lo": 0.160322,
      "emp_dfm_hi": 0.371305,
      "prob_depr_14d": 0.634016,
      "prob_depr_30d": 0.713318,
      "alarm_mass_14d": 0.303997,
      "alarm_mass_30d": 0.463338
    },
    {
      "date": "2025-12-03",
      "mid": 10.464839,
      "spread_pct": 0.23525,
      "gap": 3.504839,
      "log_depth": 13.392157,
      "z_gap": 1.85235,
      "z_spread": 2.335605,
      "z_liq": 0.486428,
      "emp": 2.972229,
      "emp_rolling": null,
      "emp_dfm": 2.092185,
      "emp_dfm_lo": 1.986694,
      "emp_dfm_hi": 2.197676,
      "prob_depr_14d": 0.516803,
      "prob_depr_30d": 0.446377,
      "alarm_mass_14d": 0.107157,
      "alarm_mass_30d": 0.091368
    },
    {
      "date": "2025-12-04",
      "mid": 10.315532,
      "spread_pct": 0.242018,
      "gap": 3.355532,
      "log_depth": 13.48333,
      "z_gap": 1.520855,
      "z_spread": 1.684966,
      "z_liq": -0.079681,
      "emp": 2.128936,
      "emp_rolling": null,
      "emp_dfm": 1.685063,
      "emp_dfm_lo": 1.579572,
      "emp_dfm_hi": 1.790555,
      "prob_depr_14d": 0.423934,
      "prob_depr_30d": 0.306976,
      "alarm_mass_14d": -0.032562,
      "alarm_mass_30d": -0.103228
    },
    {
      "date": "2025-12-05",
      "mid": 9.661205,
      "spread_pct": 0.219501,
      "gap": 2.701205,
      "log_depth": 13.56967,
      "z_gap": 0.068109,
      "z_spread": 0.48922,
      "z_liq": -0.32111,
      "emp": 0.281114,
      "emp_rolling": null,
      "emp_dfm": -0.135265,
      "emp_dfm_lo": -0.240757,
      "emp_dfm_hi": -0.029774,
      "prob_depr_14d": 0.567837,
      "prob_depr_30d": 0.57369,
      "alarm_mass_14d": 0.065206,
      "alarm_mass_30d": 0.093868
    },
    {
      "date": "2025-12-06",
      "mid": 9.639073,
      "spread_pct": 0.146208,
      "gap": 2.679073,
      "log_depth": 13.342456,
      "z_gap": 0.018972,
      "z_spread": 0.162958,
      "z_liq": -0.80527,
      "emp": -0.128511,
      "emp_rolling": null,
      "emp_dfm": -0.212027,
      "emp_dfm_lo": -0.317518,
      "emp_dfm_hi": -0.106535,
      "prob_depr_14d": 0.476741,
      "prob_depr_30d": 0.425919,
      "alarm_mass_14d": -0.03567,
      "alarm_mass_30d": -0.058962
    },
    {
      "date": "2025-12-07",
      "mid": 9.486744,
      "spread_pct": 0.123026,
      "gap": 2.526744,
      "log_depth": 13.258793,
      "z_gap": -0.31923,
      "z_spread": -0.232727,
      "z_liq": 0.069703,
      "emp": -0.346685,
      "emp_rolling": null,
      "emp_dfm": -0.635953,
      "emp_dfm_lo": -0.741444,
      "emp_dfm_hi": -0.530461,
      "prob_depr_14d": 0.479726,
      "prob_depr_30d": 0.389251,
      "alarm_mass_14d": -0.027297,
      "alarm_mass_30d": -0.077729
    },
    {
      "date": "2025-12-08",
      "mid": 9.621585,
      "spread_pct": 0.120001,
      "gap": 2.661585,
      "log_depth": 13.19871,
      "z_gap": -0.019855,
      "z_spread": -0.214263,
      "z_liq": -0.47533,
      "emp": -0.310442,
      "emp_rolling": null,
      "emp_dfm": -0.267044,
      "emp_dfm_lo": -0.372536,
      "emp_dfm_hi": -0.161553,
      "prob_depr_14d": 0.374026,
      "prob_depr_30d": 0.239483,
      "alarm_mass_14d": -0.121218,
      "alarm_mass_30d": -0.20174
    },
    {
      "date": "2025-12-09",
      "mid": 9.299366,
      "spread_pct": 0.11527,
      "gap": 2.339366,
      "log_depth": 13.519407,
      "z_gap": -0.73525,
      "z_spread": -0.450982,
      "z_liq": -0.625398,
      "emp": -0.987073,
      "emp_rolling": -2.038483,
      "emp_dfm": -1.156196,
      "emp_dfm_lo": -1.261687,
      "emp_dfm_hi": -1.050705,
      "prob_depr_14d": 0.556339,
      "prob_depr_30d": 0.563221,
      "alarm_mass_14d": 0.035418,
      "alarm_mass_30d": 0.082977
    },
    {
      "date": "2025-12-10",
      "mid": 9.336807,
      "spread_pct": 0.116611,
      "gap": 2.376807,
      "log_depth": 13.387431,
      "z_gap": -0.652124,
      "z_spread": -0.401596,
      "z_liq": -0.059881,
      "emp": -0.720884,
      "emp_rolling": -1.427592,
      "emp_dfm": -1.057662,
      "emp_dfm_lo": -1.163153,
      "emp_dfm_hi": -0.95217,
      "prob_depr_14d": 0.546307,
      "prob_depr_30d": 0.517594,
      "alarm_mass_14d": -0.003223,
      "alarm_mass_30d": -0.008012
    },
    {
      "date": "2025-12-11",
      "mid": 9.129898,
      "spread_pct": 0.1203,
      "gap": 2.169898,
      "log_depth": 13.534753,
      "z_gap": -1.111506,
      "z_spread": -0.455239,
      "z_liq": -0.442362,
      "emp": -1.177487,
      "emp_rolling": -1.803874,
      "emp_dfm": -1.628813,
      "emp_dfm_lo": -1.734304,
      "emp_dfm_hi": -1.523321,
      "prob_depr_14d": 0.685769,
      "prob_depr_30d": 0.777948,
      "alarm_mass_14d": 0.09453,
      "alarm_mass_30d": 0.185806
    },
    {
      "date": "2025-12-12",
      "mid": 9.211839,
      "spread_pct": 0.111937,
      "gap": 2.251839,
      "log_depth": 13.199843,
      "z_gap": -0.929579,
      "z_spread": -0.454087,
      "z_liq": -0.027928,
      "emp": -0.927791,
      "emp_rolling": -1.300574,
      "emp_dfm": -1.406053,
      "emp_dfm_lo": -1.511544,
      "emp_dfm_hi": -1.300561,
      "prob_depr_14d": 0.628806,
      "prob_depr_30d": 0.668395,
      "alarm_mass_14d": 0.005631,
      "alarm_mass_30d": 0.030523
    },
    {
      "date": "2025-12-13",
      "mid": 9.241627,
      "spread_pct": 0.099477,
      "gap": 2.281627,
      "log_depth": 12.9841,
      "z_gap": -0.863444,
      "z_spread": -0.384081,
      "z_liq": 0.279897,
      "emp": -0.739517,
      "emp_rolling": -0.959159,
      "emp_dfm": -1.321396,
      "emp_dfm_lo": -1.426887,
      "emp_dfm_hi": -1.215904,
      "prob_depr_14d": 0.629534,
      "prob_depr_30d": 0.656687,
      "alarm_mass_14d": -0.007963,
      "alarm_mass_30d": -0.000178
    },
    {
      "date": "2025-12-14",
      "mid": 9.221713,
      "spread_pct": 0.108608,
      "gap": 2.261713,
      "log_depth": 12.764618,
      "z_gap": -0.907657,
      "z_spread": -0.476237,
      "z_liq": -0.049213,
      "emp": -0.935503,
      "emp_rolling": -1.1458,
      "emp_dfm": -1.377041,
      "emp_dfm_lo": -1.482532,
      "emp_dfm_hi": -1.271549,
      "prob_depr_14d": 0.6143,
      "prob_depr_30d": 0.643255,
      "alarm_mass_14d": -0.033395,
      "alarm_mass_30d": -0.0255
    },
    {
      "date": "2025-12-15",
      "mid": 9.371131,
      "spread_pct": 0.100715,
      "gap": 2.411131,
      "log_depth": 13.372155,
      "z_gap": -0.575917,
      "z_spread": -0.227987,
      "z_liq": -0.298803,
      "emp": -0.626556,
      "emp_rolling": -0.792416,
      "emp_dfm": -0.962886,
      "emp_dfm_lo": -1.068378,
      "emp_dfm_hi": -0.857395,
      "prob_depr_14d": 0.572318,
      "prob_depr_30d": 0.578373,
      "alarm_mass_14d": -0.077507,
      "alarm_mass_30d": -0.097275
    },
    {
      "date": "2025-12-16",
      "mid": 9.261977,
      "spread_pct": 0.09185,
      "gap": 2.301977,
      "log_depth": 12.877179,
      "z_gap": -0.818262,
      "z_spread": -0.486185,
      "z_liq": 0.050011,
      "emp": -0.852924,
      "emp_rolling": -0.919488,
      "emp_dfm": -1.263603,
      "emp_dfm_lo": -1.369095,
      "emp_dfm_hi": -1.158112,
      "prob_depr_14d": 0.580307,
      "prob_depr_30d": 0.575963,
      "alarm_mass_14d": -0.06076,
      "alarm_mass_30d": -0.079311
    },
    {
      "date": "2025-12-17",
      "mid": 9.42351,
      "spread_pct": 0.099786,
      "gap": 2.46351,
      "log_depth": 13.136969,
      "z_gap": -0.459623,
      "z_spread": -0.133661,
      "z_liq": -1.022078,
      "emp": -0.713266,
      "emp_rolling": -0.844418,
      "emp_dfm": -0.817384,
      "emp_dfm_lo": -0.922875,
      "emp_dfm_hi": -0.711892,
      "prob_depr_14d": 0.554731,
      "prob_depr_30d": 0.580093,
      "alarm_mass_14d": -0.076152,
      "alarm_mass_30d": -0.058429
    },
    {
      "date": "2025-12-18",
      "mid": 10.488076,
      "spread_pct": 0.250088,
      "gap": 3.528076,
      "log_depth": 13.419138,
      "z_gap": 1.903941,
      "z_spread": 1.622763,
      "z_liq": 0.127849,
      "emp": 2.400805,
      "emp_rolling": 2.104695,
      "emp_dfm": 2.141644,
      "emp_dfm_lo": 2.036153,
      "emp_dfm_hi": 2.247136,
      "prob_depr_14d": 0.279938,
      "prob_depr_30d": 0.114368,
      "alarm_mass_14d": -0.280592,
      "alarm_mass_30d": -0.42147
    },
    {
      "date": "2025-12-19",
      "mid": 10.257441,
      "spread_pct": 0.225534,
      "gap": 3.297441,
      "log_depth": 13.49196,
      "z_gap": 1.391881,
      "z_spread": 1.646158,
      "z_liq": -0.692941,
      "emp": 1.825166,
      "emp_rolling": 1.382725,
      "emp_dfm": 1.524114,
      "emp_dfm_lo": 1.418622,
      "emp_dfm_hi": 1.629605,
      "prob_depr_14d": 0.453542,
      "prob_depr_30d": 0.384088,
      "alarm_mass_14d": -0.055934,
      "alarm_mass_30d": -0.075849
    },
    {
      "date": "2025-12-20",
      "mid": 9.739084,
      "spread_pct": 0.18851,
      "gap": 2.779084,
      "log_depth": 13.456763,
      "z_gap": 0.241019,
      "z_spread": 0.196531,
      "z_liq": -0.591023,
      "emp": 0.106712,
      "emp_rolling": -0.195027,
      "emp_dfm": 0.075332,
      "emp_dfm_lo": -0.030159,
      "emp_dfm_hi": 0.180824,
      "prob_depr_14d": 0.408615,
      "prob_depr_30d": 0.298218,
      "alarm_mass_14d": -0.102198,
      "alarm_mass_30d": -0.162728
    },
    {
      "date": "2025-12-21",
      "mid": 10.111467,
      "spread_pct": 0.196689,
      "gap": 3.151467,
      "log_depth": 13.306082,
      "z_gap": 1.067789,
      "z_spread": 0.995792,
      "z_liq": 0.047698,
      "emp": 1.398064,
      "emp_rolling": 1.048684,
      "emp_dfm": 1.101983,
      "emp_dfm_lo": 0.996492,
      "emp_dfm_hi": 1.207475,
      "prob_depr_14d": 0.370563,
      "prob_depr_30d": 0.219972,
      "alarm_mass_14d": -0.133443,
      "alarm_mass_30d": -0.227551
    },
    {
      "date": "2025-12-22",
      "mid": 9.732886,
      "spread_pct": 0.180074,
      "gap": 2.772886,
      "log_depth": 13.362917,
      "z_gap": 0.227258,
      "z_spread": -0.130558,
      "z_liq": -0.963039,
      "emp": -0.245155,
      "emp_rolling": -0.626339,
      "emp_dfm": 0.051794,
      "emp_dfm_lo": -0.053697,
      "emp_dfm_hi": 0.157286,
      "prob_depr_14d": 0.313145,
      "prob_depr_30d": 0.172855,
      "alarm_mass_14d": -0.174434,
      "alarm_mass_30d": -0.248623
    },
    {
      "date": "2025-12-23",
      "mid": 9.589176,
      "spread_pct": 0.161156,
      "gap": 2.629176,
      "log_depth": 13.36816,
      "z_gap": -0.09181,
      "z_spread": -0.037671,
      "z_liq": -0.716254,
      "emp": -0.311187,
      "emp_rolling": -0.67187,
      "emp_dfm": -0.350411,
      "emp_dfm_lo": -0.455902,
      "emp_dfm_hi": -0.24492,
      "prob_depr_14d": 0.453257,
      "prob_depr_30d": 0.378725,
      "alarm_mass_14d": -0.032078,
      "alarm_mass_30d": -0.03856
    },
    {
      "date": "2025-12-24",
      "mid": 9.615378,
      "spread_pct": 0.134394,
      "gap": 2.655378,
      "log_depth": 13.123002,
      "z_gap": -0.033635,
      "z_spread": -0.292617,
      "z_liq": -0.040932,
      "emp": -0.236831,
      "emp_rolling": -0.516282,
      "emp_dfm": -0.282662,
      "emp_dfm_lo": -0.388154,
      "emp_dfm_hi": -0.177171,
      "prob_depr_14d": 0.358306,
      "prob_depr_30d": 0.203139,
      "alarm_mass_14d": -0.119731,
      "alarm_mass_30d": -0.197491
    },
    {
      "date": "2025-12-25",
      "mid": 9.795829,
      "spread_pct": 0.115884,
      "gap": 2.835829,
      "log_depth": 13.019902,
      "z_gap": 0.367005,
      "z_spread": 0.099503,
      "z_liq": 0.975094,
      "emp": 0.614571,
      "emp_rolling": 0.445294,
      "emp_dfm": 0.220624,
      "emp_dfm_lo": 0.115133,
      "emp_dfm_hi": 0.326116,
      "prob_depr_14d": 0.347078,
      "prob_depr_30d": 0.161333,
      "alarm_mass_14d": -0.121972,
      "alarm_mass_30d": -0.216655
    },
    {
      "date": "2025-12-26",
      "mid": 9.621821,
      "spread_pct": 0.123674,
      "gap": 2.661821,
      "log_depth": 12.788172,
      "z_gap": -0.019331,
      "z_spread": -0.342621,
      "z_liq": -0.436701,
      "emp": -0.386573,
      "emp_rolling": -0.705576,
      "emp_dfm": -0.262042,
      "emp_dfm_lo": -0.367533,
      "emp_dfm_hi": -0.15655,
      "prob_depr_14d": 0.336022,
      "prob_depr_30d": 0.186179,
      "alarm_mass_14d": -0.111751,
      "alarm_mass_30d": -0.150078
    },
    {
      "date": "2025-12-27",
      "mid": 9.751886,
      "spread_pct": 0.124935,
      "gap": 2.791886,
      "log_depth": 12.968187,
      "z_gap": 0.269441,
      "z_spread": -0.30721,
      "z_liq": 0.675228,
      "emp": 0.175845,
      "emp_rolling": -0.032549,
      "emp_dfm": 0.09511,
      "emp_dfm_lo": -0.010382,
      "emp_dfm_hi": 0.200601,
      "prob_depr_14d": 0.263987,
      "prob_depr_30d": 0.088552,
      "alarm_mass_14d": -0.175107,
      "alarm_mass_30d": -0.233271
    },
    {
      "date": "2025-12-28",
      "mid": 9.921636,
      "spread_pct": 0.126725,
      "gap": 2.961636,
      "log_depth": 12.846008,
      "z_gap": 0.646324,
      "z_spread": 0.13572,
      "z_liq": 1.298382,
      "emp": 0.923234,
      "emp_rolling": 0.764697,
      "emp_dfm": 0.570895,
      "emp_dfm_lo": 0.465404,
      "emp_dfm_hi": 0.676386,
      "prob_depr_14d": 0.271711,
      "prob_depr_30d": 0.085394,
      "alarm_mass_14d": -0.150094,
      "alarm_mass_30d": -0.206457
    },
    {
      "date": "2025-12-29",
      "mid": 9.842258,
      "spread_pct": 0.141071,
      "gap": 2.882258,
      "log_depth": 13.053204,
      "z_gap": 0.470086,
      "z_spread": -0.115467,
      "z_liq": 0.461818,
      "emp": 0.371773,
      "emp_rolling": 0.126352,
      "emp_dfm": 0.351636,
      "emp_dfm_lo": 0.246145,
      "emp_dfm_hi": 0.457128,
      "prob_depr_14d": 0.253762,
      "prob_depr_30d": 0.084165,
      "alarm_mass_14d": -0.147179,
      "alarm_mass_30d": -0.179224
    },
    {
      "date": "2025-12-30",
      "mid": 9.64886,
      "spread_pct": 0.090075,
      "gap": 2.68886,
      "log_depth": 13.210997,
      "z_gap": 0.040701,
      "z_spread": -0.579507,
      "z_liq": -0.102303,
      "emp": -0.405813,
      "emp_rolling": -0.684634,
      "emp_dfm": -0.188646,
      "emp_dfm_lo": -0.294137,
      "emp_dfm_hi": -0.083154,
      "prob_depr_14d": 0.256111,
      "prob_depr_30d": 0.094293,
      "alarm_mass_14d": -0.11726,
      "alarm_mass_30d": -0.135418
    },
    {
      "date": "2025-12-31",
      "mid": 9.941071,
      "spread_pct": 0.129531,
      "gap": 2.981071,
      "log_depth": 13.081062,
      "z_gap": 0.689473,
      "z_spread": 0.429938,
      "z_liq": -0.002352,
      "emp": 0.745199,
      "emp_rolling": 0.481621,
      "emp_dfm": 0.62435,
      "emp_dfm_lo": 0.518859,
      "emp_dfm_hi": 0.729842,
      "prob_depr_14d": 0.329913,
      "prob_depr_30d": 0.168193,
      "alarm_mass_14d": -0.036896,
      "alarm_mass_30d": -0.050841
    },
    {
      "date": "2026-01-01",
      "mid": 9.863781,
      "spread_pct": 0.140252,
      "gap": 2.903781,
      "log_depth": 13.180519,
      "z_gap": 0.517872,
      "z_spread": -0.155609,
      "z_liq": 0.197221,
      "emp": 0.291923,
      "emp_rolling": 0.057306,
      "emp_dfm": 0.410704,
      "emp_dfm_lo": 0.305213,
      "emp_dfm_hi": 0.516195,
      "prob_depr_14d": 0.229813,
      "prob_depr_30d": 0.07038,
      "alarm_mass_14d": -0.134584,
      "alarm_mass_30d": -0.147887
    },
    {
      "date": "2026-01-02",
      "mid": 9.65483,
      "spread_pct": 0.127257,
      "gap": 2.69483,
      "log_depth": 13.311794,
      "z_gap": 0.053956,
      "z_spread": -0.472816,
      "z_liq": -0.989758,
      "emp": -0.602759,
      "emp_rolling": -0.945265,
      "emp_dfm": -0.171583,
      "emp_dfm_lo": -0.277074,
      "emp_dfm_hi": -0.066092,
      "prob_depr_14d": 0.273843,
      "prob_depr_30d": 0.127878,
      "alarm_mass_14d": -0.082175,
      "alarm_mass_30d": -0.079667
    },
    {
      "date": "2026-01-03",
      "mid": 9.846242,
      "spread_pct": 0.122656,
      "gap": 2.886242,
      "log_depth": 13.311937,
      "z_gap": 0.478931,
      "z_spread": -0.053515,
      "z_liq": -0.171543,
      "emp": 0.221017,
      "emp_rolling": 0.021853,
      "emp_dfm": 0.357767,
      "emp_dfm_lo": 0.252275,
      "emp_dfm_hi": 0.463258,
      "prob_depr_14d": 0.262859,
      "prob_depr_30d": 0.101967,
      "alarm_mass_14d": -0.090046,
      "alarm_mass_30d": -0.104049
    },
    {
      "date": "2026-01-04",
      "mid": 10.05699,
      "spread_pct": 0.173831,
      "gap": 3.09699,
      "log_depth": 13.207229,
      "z_gap": 0.946838,
      "z_spread": 0.423966,
      "z_liq": 0.72206,
      "emp": 1.13665,
      "emp_rolling": 1.082468,
      "emp_dfm": 0.948413,
      "emp_dfm_lo": 0.842921,
      "emp_dfm_hi": 1.053904,
      "prob_depr_14d": 0.254935,
      "prob_depr_30d": 0.081843,
      "alarm_mass_14d": -0.096424,
      "alarm_mass_30d": -0.119437
    },
    {
      "date": "2026-01-05",
      "mid": 10.307109,
      "spread_pct": 0.20504,
      "gap": 3.347109,
      "log_depth": 13.048626,
      "z_gap": 1.502155,
      "z_spread": 1.224844,
      "z_liq": -0.934456,
      "emp": 1.530092,
      "emp_rolling": 1.351177,
      "emp_dfm": 1.64884,
      "emp_dfm_lo": 1.543349,
      "emp_dfm_hi": 1.754331,
      "prob_depr_14d": 0.288461,
      "prob_depr_30d": 0.145528,
      "alarm_mass_14d": -0.061081,
      "alarm_mass_30d": -0.05033
    },
    {
      "date": "2026-01-06",
      "mid": 10.433365,
      "spread_pct": 0.247789,
      "gap": 3.473365,
      "log_depth": 13.662641,
      "z_gap": 1.782471,
      "z_spread": 1.691959,
      "z_liq": -0.973659,
      "emp": 2.022865,
      "emp_rolling": 1.744333,
      "emp_dfm": 2.006461,
      "emp_dfm_lo": 1.90097,
      "emp_dfm_hi": 2.111953,
      "prob_depr_14d": 0.329436,
      "prob_depr_30d": 0.198325,
      "alarm_mass_14d": -0.022687,
      "alarm_mass_30d": -0.009135
    },
    {
      "date": "2026-01-07",
      "mid": 10.568177,
      "spread_pct": 0.242269,
      "gap": 3.608177,
      "log_depth": 13.765329,
      "z_gap": 2.081783,
      "z_spread": 1.638328,
      "z_liq": -0.455136,
      "emp": 2.343945,
      "emp_rolling": 2.094973,
      "emp_dfm": 2.38073,
      "emp_dfm_lo": 2.275238,
      "emp_dfm_hi": 2.486221,
      "prob_depr_14d": 0.230647,
      "prob_depr_30d": 0.081675,
      "alarm_mass_14d": -0.125624,
      "alarm_mass_30d": -0.142667
    },
    {
      "date": "2026-01-08",
      "mid": 10.05791,
      "spread_pct": 0.238473,
      "gap": 3.09791,
      "log_depth": 13.714643,
      "z_gap": 0.94888,
      "z_spread": 0.650429,
      "z_liq": -1.845287,
      "emp": 0.486505,
      "emp_rolling": 0.090716,
      "emp_dfm": 0.96396,
      "emp_dfm_lo": 0.858468,
      "emp_dfm_hi": 1.069451,
      "prob_depr_14d": 0.29688,
      "prob_depr_30d": 0.178371,
      "alarm_mass_14d": -0.044085,
      "alarm_mass_30d": -0.027592
    },
    {
      "date": "2026-01-09",
      "mid": 10.149831,
      "spread_pct": 0.173385,
      "gap": 3.189831,
      "log_depth": 13.817026,
      "z_gap": 1.152965,
      "z_spread": 0.312494,
      "z_liq": -0.159901,
      "emp": 0.916422,
      "emp_rolling": 0.658415,
      "emp_dfm": 1.206543,
      "emp_dfm_lo": 1.101051,
      "emp_dfm_hi": 1.312034,
      "prob_depr_14d": 0.175349,
      "prob_depr_30d": 0.04157,
      "alarm_mass_14d": -0.160527,
      "alarm_mass_30d": -0.168301
    },
    {
      "date": "2026-01-10",
      "mid": 10.505259,
      "spread_pct": 0.168802,
      "gap": 3.545259,
      "log_depth": 13.271051,
      "z_gap": 1.94209,
      "z_spread": 1.294809,
      "z_liq": -0.305881,
      "emp": 2.062734,
      "emp_rolling": 1.701088,
      "emp_dfm": 2.198568,
      "emp_dfm_lo": 2.093077,
      "emp_dfm_hi": 2.30406,
      "prob_depr_14d": 0.191545,
      "prob_depr_30d": 0.052493,
      "alarm_mass_14d": -0.118288,
      "alarm_mass_30d": -0.125696
    },
    {
      "date": "2026-01-11",
      "mid": 10.490139,
      "spread_pct": 0.205052,
      "gap": 3.530139,
      "log_depth": 13.611493,
      "z_gap": 1.908521,
      "z_spread": 1.395046,
      "z_liq": -0.468913,
      "emp": 2.05878,
      "emp_rolling": 1.606858,
      "emp_dfm": 2.164202,
      "emp_dfm_lo": 2.058711,
      "emp_dfm_hi": 2.269694,
      "prob_depr_14d": 0.220001,
      "prob_depr_30d": 0.073461,
      "alarm_mass_14d": -0.074856,
      "alarm_mass_30d": -0.086714
    },
    {
      "date": "2026-01-12",
      "mid": 9.694159,
      "spread_pct": 0.097343,
      "gap": 2.734159,
      "log_depth": 13.500492,
      "z_gap": 0.141274,
      "z_spread": -0.679738,
      "z_liq": -1.143769,
      "emp": -0.73722,
      "emp_rolling": -1.063548,
      "emp_dfm": -0.053829,
      "emp_dfm_lo": -0.15932,
      "emp_dfm_hi": 0.051662,
      "prob_depr_14d": 0.201486,
      "prob_depr_30d": 0.066378,
      "alarm_mass_14d": -0.073065,
      "alarm_mass_30d": -0.072006
    },
    {
      "date": "2026-01-13",
      "mid": 9.960334,
      "spread_pct": 0.127056,
      "gap": 3.000334,
      "log_depth": 13.691337,
      "z_gap": 0.732239,
      "z_spread": 0.036681,
      "z_liq": -0.967182,
      "emp": 0.197929,
      "emp_rolling": -0.193017,
      "emp_dfm": 0.673454,
      "emp_dfm_lo": 0.567963,
      "emp_dfm_hi": 0.778945,
      "prob_depr_14d": 0.212154,
      "prob_depr_30d": 0.072725,
      "alarm_mass_14d": -0.063579,
      "alarm_mass_30d": -0.066142
    },
    {
      "date": "2026-01-14",
      "mid": 9.620808,
      "spread_pct": 0.128628,
      "gap": 2.660808,
      "log_depth": 13.67573,
      "z_gap": -0.02158,
      "z_spread": -0.851777,
      "z_liq": -1.831165,
      "emp": -1.178377,
      "emp_rolling": -1.577923,
      "emp_dfm": -0.26839,
      "emp_dfm_lo": -0.373882,
      "emp_dfm_hi": -0.162899,
      "prob_depr_14d": 0.200678,
      "prob_depr_30d": 0.074236,
      "alarm_mass_14d": -0.069042,
      "alarm_mass_30d": -0.057814
    },
    {
      "date": "2026-01-15",
      "mid": 9.735421,
      "spread_pct": 0.093009,
      "gap": 2.775421,
      "log_depth": 13.815411,
      "z_gap": 0.232885,
      "z_spread": -0.606699,
      "z_liq": -0.919806,
      "emp": -0.556647,
      "emp_rolling": -0.921086,
      "emp_dfm": 0.045041,
      "emp_dfm_lo": -0.060451,
      "emp_dfm_hi": 0.150532,
      "prob_depr_14d": 0.196217,
      "prob_depr_30d": 0.060228,
      "alarm_mass_14d": -0.068818,
      "alarm_mass_30d": -0.065462
    },
    {
      "date": "2026-01-16",
      "mid": 9.691887,
      "spread_pct": 0.101423,
      "gap": 2.731887,
      "log_depth": 13.813168,
      "z_gap": 0.136231,
      "z_spread": -0.266293,
      "z_liq": -1.934452,
      "emp": -0.70383,
      "emp_rolling": -1.166987,
      "emp_dfm": -0.070578,
      "emp_dfm_lo": -0.176069,
      "emp_dfm_hi": 0.034914,
      "prob_depr_14d": 0.297751,
      "prob_depr_30d": 0.180033,
      "alarm_mass_14d": 0.036864,
      "alarm_mass_30d": 0.059487
    },
    {
      "date": "2026-01-17",
      "mid": 10.518596,
      "spread_pct": 0.14189,
      "gap": 3.558596,
      "log_depth": 13.802438,
      "z_gap": 1.971701,
      "z_spread": 1.657469,
      "z_liq": 0.636225,
      "emp": 2.62887,
      "emp_rolling": 2.253007,
      "emp_dfm": 2.231594,
      "emp_dfm_lo": 2.126103,
      "emp_dfm_hi": 2.337086,
      "prob_depr_14d": 0.27219,
      "prob_depr_30d": 0.098269,
      "alarm_mass_14d": 0.00057,
      "alarm_mass_30d": -0.033501
    },
    {
      "date": "2026-01-18",
      "mid": 10.115854,
      "spread_pct": 0.206419,
      "gap": 3.155854,
      "log_depth": 13.236053,
      "z_gap": 1.077529,
      "z_spread": 0.902732,
      "z_liq": -0.138666,
      "emp": 1.281511,
      "emp_rolling": 0.787867,
      "emp_dfm": 1.127088,
      "emp_dfm_lo": 1.021597,
      "emp_dfm_hi": 1.232579,
      "prob_depr_14d": 0.338335,
      "prob_depr_30d": 0.183245,
      "alarm_mass_14d": 0.054315,
      "alarm_mass_30d": 0.045152
    },
    {
      "date": "2026-01-19",
      "mid": 10.178148,
      "spread_pct": 0.15858,
      "gap": 3.218148,
      "log_depth": 13.47947,
      "z_gap": 1.215835,
      "z_spread": 0.505048,
      "z_liq": 0.025913,
      "emp": 1.148792,
      "emp_rolling": 0.66688,
      "emp_dfm": 1.287869,
      "emp_dfm_lo": 1.182378,
      "emp_dfm_hi": 1.393361,
      "prob_depr_14d": 0.200192,
      "prob_depr_30d": 0.053849,
      "alarm_mass_14d": -0.080899,
      "alarm_mass_30d": -0.080466
    },
    {
      "date": "2026-01-20",
      "mid": 9.695116,
      "spread_pct": 0.121955,
      "gap": 2.735116,
      "log_depth": 13.302771,
      "z_gap": 0.143399,
      "z_spread": -0.792731,
      "z_liq": -1.167052,
      "emp": -0.821181,
      "emp_rolling": -1.482471,
      "emp_dfm": -0.058094,
      "emp_dfm_lo": -0.163586,
      "emp_dfm_hi": 0.047397,
      "prob_depr_14d": 0.178362,
      "prob_depr_30d": 0.051082,
      "alarm_mass_14d": -0.089799,
      "alarm_mass_30d": -0.068835
    },
    {
      "date": "2026-01-21",
      "mid": 9.616985,
      "spread_pct": 0.096845,
      "gap": 2.656985,
      "log_depth": 13.709479,
      "z_gap": -0.030069,
      "z_spread": -0.935909,
      "z_liq": -1.79505,
      "emp": -1.230633,
      "emp_rolling": -1.990599,
      "emp_dfm": -0.284546,
      "emp_dfm_lo": -0.390038,
      "emp_dfm_hi": -0.179055,
      "prob_depr_14d": 0.185793,
      "prob_depr_30d": 0.062388,
      "alarm_mass_14d": -0.074294,
      "alarm_mass_30d": -0.05031
    },
    {
      "date": "2026-01-22",
      "mid": 9.586059,
      "spread_pct": 0.079542,
      "gap": 2.626059,
      "log_depth": 13.702066,
      "z_gap": -0.098729,
      "z_spread": -0.990342,
      "z_liq": -1.004028,
      "emp": -1.064035,
      "emp_rolling": -1.76034,
      "emp_dfm": -0.371125,
      "emp_dfm_lo": -0.476617,
      "emp_dfm_hi": -0.265634,
      "prob_depr_14d": 0.1943,
      "prob_depr_30d": 0.059536,
      "alarm_mass_14d": -0.060167,
      "alarm_mass_30d": -0.048301
    },
    {
      "date": "2026-01-23",
      "mid": 9.640237,
      "spread_pct": 0.083209,
      "gap": 2.680237,
      "log_depth": 13.454255,
      "z_gap": 0.021557,
      "z_spread": -0.469521,
      "z_liq": -0.565666,
      "emp": -0.488142,
      "emp_rolling": -1.0892,
      "emp_dfm": -0.216515,
      "emp_dfm_lo": -0.322006,
      "emp_dfm_hi": -0.111024,
      "prob_depr_14d": 0.287012,
      "prob_depr_30d": 0.132443,
      "alarm_mass_14d": 0.03303,
      "alarm_mass_30d": 0.027404
    },
    {
      "date": "2026-01-24",
      "mid": 9.616324,
      "spread_pct": 0.080834,
      "gap": 2.656324,
      "log_depth": 13.407285,
      "z_gap": -0.031536,
      "z_spread": -0.835333,
      "z_liq": -0.955468,
      "emp": -0.897961,
      "emp_rolling": -1.448597,
      "emp_dfm": -0.285563,
      "emp_dfm_lo": -0.391054,
      "emp_dfm_hi": -0.180071,
      "prob_depr_14d": 0.211051,
      "prob_depr_30d": 0.070887,
      "alarm_mass_14d": -0.042021,
      "alarm_mass_30d": -0.031214
    },
    {
      "date": "2026-01-25",
      "mid": 9.638152,
      "spread_pct": 0.090018,
      "gap": 2.678152,
      "log_depth": 13.272753,
      "z_gap": 0.016928,
      "z_spread": -0.330178,
      "z_liq": -0.530712,
      "emp": -0.383946,
      "emp_rolling": -0.874015,
      "emp_dfm": -0.220265,
      "emp_dfm_lo": -0.325756,
      "emp_dfm_hi": -0.114773,
      "prob_depr_14d": 0.327117,
      "prob_depr_30d": 0.177731,
      "alarm_mass_14d": 0.067424,
      "alarm_mass_30d": 0.072865
    },
    {
      "date": "2026-01-26",
      "mid": 9.441188,
      "spread_pct": 0.067198,
      "gap": 2.481188,
      "log_depth": 13.5826,
      "z_gap": -0.420375,
      "z_spread": -0.84878,
      "z_liq": -1.818132,
      "emp": -1.431956,
      "emp_rolling": -1.982137,
      "emp_dfm": -0.769787,
      "emp_dfm_lo": -0.875279,
      "emp_dfm_hi": -0.664296,
      "prob_depr_14d": 0.312017,
      "prob_depr_30d": 0.194433,
      "alarm_mass_14d": 0.048745,
      "alarm_mass_30d": 0.085275
    },
    {
      "date": "2026-01-27",
      "mid": 9.294668,
      "spread_pct": 0.061197,
      "gap": 2.334668,
      "log_depth": 13.874298,
      "z_gap": -0.745681,
      "z_spread": -1.092635,
      "z_liq": -1.017736,
      "emp": -1.560363,
      "emp_rolling": -2.01609,
      "emp_dfm": -1.179323,
      "emp_dfm_lo": -1.284814,
      "emp_dfm_hi": -1.073832,
      "prob_depr_14d": 0.353638,
      "prob_depr_30d": 0.226401,
      "alarm_mass_14d": 0.06306,
      "alarm_mass_30d": 0.079656
    },
    {
      "date": "2026-01-28",
      "mid": 9.103055,
      "spread_pct": 0.093759,
      "gap": 2.143055,
      "log_depth": 13.555029,
      "z_gap": -1.171101,
      "z_spread": -0.648041,
      "z_liq": -1.385401,
      "emp": -1.646165,
      "emp_rolling": -2.121719,
      "emp_dfm": -1.706548,
      "emp_dfm_lo": -1.812039,
      "emp_dfm_hi": -1.601056,
      "prob_depr_14d": 0.643004,
      "prob_depr_30d": 0.745325,
      "alarm_mass_14d": 0.293769,
      "alarm_mass_30d": 0.512049
    },
    {
      "date": "2026-01-29",
      "mid": 9.018646,
      "spread_pct": 0.082672,
      "gap": 2.058646,
      "log_depth": 13.667656,
      "z_gap": -1.358508,
      "z_spread": -0.708289,
      "z_liq": -0.981323,
      "emp": -1.682682,
      "emp_rolling": -2.034154,
      "emp_dfm": -1.943104,
      "emp_dfm_lo": -2.048595,
      "emp_dfm_hi": -1.837612,
      "prob_depr_14d": 0.689721,
      "prob_depr_30d": 0.800285,
      "alarm_mass_14d": 0.279124,
      "alarm_mass_30d": 0.470503
    },
    {
      "date": "2026-01-30",
      "mid": 9.256031,
      "spread_pct": 0.075015,
      "gap": 2.296031,
      "log_depth": 13.518298,
      "z_gap": -0.831463,
      "z_spread": -0.531008,
      "z_liq": -0.437563,
      "emp": -1.045891,
      "emp_rolling": -1.241714,
      "emp_dfm": -1.287362,
      "emp_dfm_lo": -1.392854,
      "emp_dfm_hi": -1.181871,
      "prob_depr_14d": 0.567097,
      "prob_depr_30d": 0.57408,
      "alarm_mass_14d": 0.116862,
      "alarm_mass_30d": 0.181894
    },
    {
      "date": "2026-01-31",
      "mid": 9.206231,
      "spread_pct": 0.094646,
      "gap": 2.246231,
      "log_depth": 13.471142,
      "z_gap": -0.94203,
      "z_spread": -0.744543,
      "z_liq": -0.781586,
      "emp": -1.373598,
      "emp_rolling": -1.501309,
      "emp_dfm": -1.422967,
      "emp_dfm_lo": -1.528458,
      "emp_dfm_hi": -1.317476,
      "prob_depr_14d": 0.536177,
      "prob_depr_30d": 0.531955,
      "alarm_mass_14d": 0.05038,
      "alarm_mass_30d": 0.086491
    },
    {
      "date": "2026-02-01",
      "mid": 9.091444,
      "spread_pct": 0.080767,
      "gap": 2.131444,
      "log_depth": 13.576221,
      "z_gap": -1.196882,
      "z_spread": -0.621514,
      "z_liq": -0.450516,
      "emp": -1.35047,
      "emp_rolling": -1.395125,
      "emp_dfm": -1.738993,
      "emp_dfm_lo": -1.844484,
      "emp_dfm_hi": -1.633501,
      "prob_depr_14d": 0.665994,
      "prob_depr_30d": 0.747292,
      "alarm_mass_14d": 0.146269,
      "alarm_mass_30d": 0.246682
    },
    {
      "date": "2026-02-02",
      "mid": 9.188664,
      "spread_pct": 0.07819,
      "gap": 2.228664,
      "log_depth": 13.454976,
      "z_gap": -0.981031,
      "z_spread": -0.929989,
      "z_liq": -0.433972,
      "emp": -1.417666,
      "emp_rolling": -1.389202,
      "emp_dfm": -1.475924,
      "emp_dfm_lo": -1.581415,
      "emp_dfm_hi": -1.370433,
      "prob_depr_14d": 0.493172,
      "prob_depr_30d": 0.434531,
      "alarm_mass_14d": -0.035717,
      "alarm_mass_30d": -0.079261
    },
    {
      "date": "2026-02-03",
      "mid": 9.183537,
      "spread_pct": 0.065945,
      "gap": 2.223537,
      "log_depth": 13.434138,
      "z_gap": -0.992416,
      "z_spread": -1.105939,
      "z_liq": -0.753176,
      "emp": -1.64701,
      "emp_rolling": -1.57186,
      "emp_dfm": -1.490442,
      "emp_dfm_lo": -1.595933,
      "emp_dfm_hi": -1.38495,
      "prob_depr_14d": 0.43811,
      "prob_depr_30d": 0.350173,
      "alarm_mass_14d": -0.089106,
      "alarm_mass_30d": -0.156374
    },
    {
      "date": "2026-02-04",
      "mid": 9.321023,
      "spread_pct": 0.065309,
      "gap": 2.361023,
      "log_depth": 13.263267,
      "z_gap": -0.687167,
      "z_spread": -0.495205,
      "z_liq": 0.174886,
      "emp": -0.734472,
      "emp_rolling": -0.600645,
      "emp_dfm": -1.104115,
      "emp_dfm_lo": -1.209606,
      "emp_dfm_hi": -0.998623,
      "prob_depr_14d": 0.530778,
      "prob_depr_30d": 0.476797,
      "alarm_mass_14d": 0.006966,
      "alarm_mass_30d": -0.019369
    },
    {
      "date": "2026-02-05",
      "mid": 9.25715,
      "spread_pct": 0.082605,
      "gap": 2.29715,
      "log_depth": 13.444862,
      "z_gap": -0.828978,
      "z_spread": -0.819081,
      "z_liq": -0.828579,
      "emp": -1.366216,
      "emp_rolling": -1.265596,
      "emp_dfm": -1.282075,
      "emp_dfm_lo": -1.387567,
      "emp_dfm_hi": -1.176584,
      "prob_depr_14d": 0.470126,
      "prob_depr_30d": 0.411391,
      "alarm_mass_14d": -0.051619,
      "alarm_mass_30d": -0.079331
    },
    {
      "date": "2026-02-06",
      "mid": 9.288909,
      "spread_pct": 0.074736,
      "gap": 2.328909,
      "log_depth": 13.617357,
      "z_gap": -0.758467,
      "z_spread": -0.617857,
      "z_liq": -0.689323,
      "emp": -1.137532,
      "emp_rolling": -1.024388,
      "emp_dfm": -1.193445,
      "emp_dfm_lo": -1.298937,
      "emp_dfm_hi": -1.087954,
      "prob_depr_14d": 0.510496,
      "prob_depr_30d": 0.479968,
      "alarm_mass_14d": -0.008224,
      "alarm_mass_30d": -0.004947
    },
    {
      "date": "2026-02-07",
      "mid": 9.115103,
      "spread_pct": 0.092827,
      "gap": 2.155103,
      "log_depth": 13.405568,
      "z_gap": -1.144352,
      "z_spread": -0.373162,
      "z_liq": -0.565554,
      "emp": -1.180973,
      "emp_rolling": -1.064697,
      "emp_dfm": -1.669813,
      "emp_dfm_lo": -1.775304,
      "emp_dfm_hi": -1.564322,
      "prob_depr_14d": 0.717356,
      "prob_depr_30d": 0.826443,
      "alarm_mass_14d": 0.1912,
      "alarm_mass_30d": 0.33032
    },
    {
      "date": "2026-02-08",
      "mid": 9.198281,
      "spread_pct": 0.093436,
      "gap": 2.238281,
      "log_depth": 13.483728,
      "z_gap": -0.959681,
      "z_spread": -0.819688,
      "z_liq": -0.86412,
      "emp": -1.46295,
      "emp_rolling": -1.315618,
      "emp_dfm": -1.448248,
      "emp_dfm_lo": -1.55374,
      "emp_dfm_hi": -1.342757,
      "prob_depr_14d": 0.517709,
      "prob_depr_30d": 0.501097,
      "alarm_mass_14d": -0.015268,
      "alarm_mass_30d": -0.005417
    },
    {
      "date": "2026-02-09",
      "mid": 9.17508,
      "spread_pct": 0.072421,
      "gap": 2.21508,
      "log_depth": 13.788466,
      "z_gap": -1.011191,
      "z_spread": -0.881885,
      "z_liq": -0.519575,
      "emp": -1.431031,
      "emp_rolling": -1.22458,
      "emp_dfm": -1.511097,
      "emp_dfm_lo": -1.616588,
      "emp_dfm_hi": -1.405606,
      "prob_depr_14d": 0.519192,
      "prob_depr_30d": 0.487065,
      "alarm_mass_14d": -0.014928,
      "alarm_mass_30d": -0.022899
    },
    {
      "date": "2026-02-10",
      "mid": 9.198588,
      "spread_pct": 0.069003,
      "gap": 2.238588,
      "log_depth": 13.77619,
      "z_gap": -0.958998,
      "z_spread": -0.701973,
      "z_liq": -0.762659,
      "emp": -1.349301,
      "emp_rolling": -1.150042,
      "emp_dfm": -1.44507,
      "emp_dfm_lo": -1.550561,
      "emp_dfm_hi": -1.339578,
      "prob_depr_14d": 0.556201,
      "prob_depr_30d": 0.568537,
      "alarm_mass_14d": 0.019863,
      "alarm_mass_30d": 0.053449
    },
    {
      "date": "2026-02-11",
      "mid": 9.235819,
      "spread_pct": 0.072489,
      "gap": 2.275819,
      "log_depth": 13.679614,
      "z_gap": -0.876339,
      "z_spread": -0.532571,
      "z_liq": -0.510013,
      "emp": -1.098997,
      "emp_rolling": -0.867454,
      "emp_dfm": -1.339955,
      "emp_dfm_lo": -1.445447,
      "emp_dfm_hi": -1.234464,
      "prob_depr_14d": 0.582192,
      "prob_depr_30d": 0.605344,
      "alarm_mass_14d": 0.043587,
      "alarm_mass_30d": 0.085793
    },
    {
      "date": "2026-02-12",
      "mid": 9.23407,
      "spread_pct": 0.069853,
      "gap": 2.27407,
      "log_depth": 13.481872,
      "z_gap": -0.880221,
      "z_spread": -0.957377,
      "z_liq": -0.669025,
      "emp": -1.444877,
      "emp_rolling": -1.160407,
      "emp_dfm": -1.348542,
      "emp_dfm_lo": -1.454033,
      "emp_dfm_hi": -1.24305,
      "prob_depr_14d": 0.445562,
      "prob_depr_30d": 0.359893,
      "alarm_mass_14d": -0.092183,
      "alarm_mass_30d": -0.15659
    },
    {
      "date": "2026-02-13",
      "mid": 9.258741,
      "spread_pct": 0.070705,
      "gap": 2.298741,
      "log_depth": 13.590955,
      "z_gap": -0.825447,
      "z_spread": -0.313716,
      "z_liq": -0.275754,
      "emp": -0.841024,
      "emp_rolling": -0.553276,
      "emp_dfm": -1.273636,
      "emp_dfm_lo": -1.379127,
      "emp_dfm_hi": -1.168144,
      "prob_depr_14d": 0.633705,
      "prob_depr_30d": 0.687836,
      "alarm_mass_14d": 0.092898,
      "alarm_mass_30d": 0.166097
    },
    {
      "date": "2026-02-14",
      "mid": 9.335413,
      "spread_pct": 0.089568,
      "gap": 2.375413,
      "log_depth": 13.37545,
      "z_gap": -0.655217,
      "z_spread": 0.010229,
      "z_liq": 0.570362,
      "emp": -0.240234,
      "emp_rolling": 0.110047,
      "emp_dfm": -1.057492,
      "emp_dfm_lo": -1.162983,
      "emp_dfm_hi": -0.952001,
      "prob_depr_14d": 0.67795,
      "prob_depr_30d": 0.730756,
      "alarm_mass_14d": 0.127644,
      "alarm_mass_30d": 0.194013
    },
    {
      "date": "2026-02-15",
      "mid": 9.061144,
      "spread_pct": 0.146075,
      "gap": 2.101144,
      "log_depth": 12.939987,
      "z_gap": -1.264154,
      "z_spread": -0.651827,
      "z_liq": -0.851564,
      "emp": -1.54141,
      "emp_rolling": -1.21938,
      "emp_dfm": -1.820899,
      "emp_dfm_lo": -1.926391,
      "emp_dfm_hi": -1.715408,
      "prob_depr_14d": 0.676393,
      "prob_depr_30d": 0.777118,
      "alarm_mass_14d": 0.10996,
      "alarm_mass_30d": 0.21668
    },
    {
      "date": "2026-02-16",
      "mid": 9.095246,
      "spread_pct": 0.079027,
      "gap": 2.135246,
      "log_depth": 13.53528,
      "z_gap": -1.18844,
      "z_spread": -0.216516,
      "z_liq": -0.365207,
      "emp": -1.038489,
      "emp_rolling": -0.697466,
      "emp_dfm": -1.726931,
      "emp_dfm_lo": -1.832422,
      "emp_dfm_hi": -1.621439,
      "prob_depr_14d": 0.769554,
      "prob_depr_30d": 0.884614,
      "alarm_mass_14d": 0.193742,
      "alarm_mass_30d": 0.309054
    },
    {
      "date": "2026-02-17",
      "mid": 9.269883,
      "spread_pct": 0.099362,
      "gap": 2.309883,
      "log_depth": 13.219908,
      "z_gap": -0.800709,
      "z_spread": -0.211743,
      "z_liq": 0.469514,
      "emp": -0.519997,
      "emp_rolling": -0.113011,
      "emp_dfm": -1.243608,
      "emp_dfm_lo": -1.3491,
      "emp_dfm_hi": -1.138117,
      "prob_depr_14d": 0.660921,
      "prob_depr_30d": 0.704919,
      "alarm_mass_14d": 0.072103,
      "alarm_mass_30d": 0.109425
    },
    {
      "date": "2026-02-18",
      "mid": 9.169336,
      "spread_pct": 0.096699,
      "gap": 2.209336,
      "log_depth": 13.269022,
      "z_gap": -1.023944,
      "z_spread": -0.705705,
      "z_liq": -0.032425,
      "emp": -1.164404,
      "emp_rolling": -0.712593,
      "emp_dfm": -1.523344,
      "emp_dfm_lo": -1.628835,
      "emp_dfm_hi": -1.417853,
      "prob_depr_14d": 0.584052,
      "prob_depr_30d": 0.58603,
      "alarm_mass_14d": -0.017234,
      "alarm_mass_30d": -0.02801
    },
    {
      "date": "2026-02-19",
      "mid": 9.274686,
      "spread_pct": 0.079034,
      "gap": 2.314686,
      "log_depth": 13.592868,
      "z_gap": -0.790046,
      "z_spread": -0.247124,
      "z_liq": -1.042896,
      "emp": -1.013376,
      "emp_rolling": -0.660975,
      "emp_dfm": -1.230871,
      "emp_dfm_lo": -1.336362,
      "emp_dfm_hi": -1.12538,
      "prob_depr_14d": 0.636073,
      "prob_depr_30d": 0.722667,
      "alarm_mass_14d": 0.02765,
      "alarm_mass_30d": 0.093963
    },
    {
      "date": "2026-02-20",
      "mid": 9.116472,
      "spread_pct": 0.099553,
      "gap": 2.156472,
      "log_depth": 13.557225,
      "z_gap": -1.141313,
      "z_spread": -0.892971,
      "z_liq": -0.50735,
      "emp": -1.519592,
      "emp_rolling": -0.999843,
      "emp_dfm": -1.671478,
      "emp_dfm_lo": -1.776969,
      "emp_dfm_hi": -1.565986,
      "prob_depr_14d": 0.563249,
      "prob_depr_30d": 0.568888,
      "alarm_mass_14d": -0.051704,
      "alarm_mass_30d": -0.07084
    },
    {
      "date": "2026-02-21",
      "mid": 9.165522,
      "spread_pct": 0.085114,
      "gap": 2.205522,
      "log_depth": 13.173366,
      "z_gap": -1.032412,
      "z_spread": -0.766465,
      "z_liq": -0.893068,
      "emp": -1.482682,
      "emp_rolling": -0.972104,
      "emp_dfm": -1.538133,
      "emp_dfm_lo": -1.643625,
      "emp_dfm_hi": -1.432642,
      "prob_depr_14d": 0.56121,
      "prob_depr_30d": 0.583694,
      "alarm_mass_14d": -0.051489,
      "alarm_mass_30d": -0.048086
    },
    {
      "date": "2026-02-22",
      "mid": 9.002518,
      "spread_pct": 0.073677,
      "gap": 2.042518,
      "log_depth": 13.680775,
      "z_gap": -1.394316,
      "z_spread": -1.038801,
      "z_liq": -1.457571,
      "emp": -2.08407,
      "emp_rolling": -1.555402,
      "emp_dfm": -1.990309,
      "emp_dfm_lo": -2.0958,
      "emp_dfm_hi": -1.884818,
      "prob_depr_14d": 0.60056,
      "prob_depr_30d": 0.677994,
      "alarm_mass_14d": -0.016613,
      "alarm_mass_30d": 0.033533
    },
    {
      "date": "2026-02-23",
      "mid": 9.009658,
      "spread_pct": 0.055471,
      "gap": 2.049658,
      "log_depth": 13.633152,
      "z_gap": -1.378464,
      "z_spread": -0.76891,
      "z_liq": -1.593414,
      "emp": -1.930138,
      "emp_rolling": -1.395616,
      "emp_dfm": -1.970978,
      "emp_dfm_lo": -2.07647,
      "emp_dfm_hi": -1.865487,
      "prob_depr_14d": 0.674881,
      "prob_depr_30d": 0.798525,
      "alarm_mass_14d": 0.063075,
      "alarm_mass_30d": 0.161927
    },
    {
      "date": "2026-02-24",
      "mid": 9.216173,
      "spread_pct": 0.075895,
      "gap": 2.256173,
      "log_depth": 13.977321,
      "z_gap": -0.919955,
      "z_spread": -0.412402,
      "z_liq": -0.568261,
      "emp": -1.062761,
      "emp_rolling": -0.403863,
      "emp_dfm": -1.396446,
      "emp_dfm_lo": -1.501937,
      "emp_dfm_hi": -1.290954,
      "prob_depr_14d": 0.63415,
      "prob_depr_30d": 0.700237,
      "alarm_mass_14d": 0.018657,
      "alarm_mass_30d": 0.052148
    },
    {
      "date": "2026-02-25",
      "mid": 9.161003,
      "spread_pct": 0.100806,
      "gap": 2.201003,
      "log_depth": 13.481336,
      "z_gap": -1.042447,
      "z_spread": -0.528494,
      "z_liq": -0.488442,
      "emp": -1.197587,
      "emp_rolling": -0.527412,
      "emp_dfm": -1.545997,
      "emp_dfm_lo": -1.651489,
      "emp_dfm_hi": -1.440506,
      "prob_depr_14d": 0.641589,
      "prob_depr_30d": 0.709197,
      "alarm_mass_14d": 0.022064,
      "alarm_mass_30d": 0.054416
    },
    {
      "date": "2026-02-26",
      "mid": 9.167345,
      "spread_pct": 0.081297,
      "gap": 2.207345,
      "log_depth": 13.526286,
      "z_gap": -1.028366,
      "z_spread": -0.533601,
      "z_liq": -0.812961,
      "emp": -1.294055,
      "emp_rolling": -0.621615,
      "emp_dfm": -1.52985,
      "emp_dfm_lo": -1.635342,
      "emp_dfm_hi": -1.424359,
      "prob_depr_14d": 0.632913,
      "prob_depr_30d": 0.707603,
      "alarm_mass_14d": 0.013242,
      "alarm_mass_30d": 0.052113
    },
    {
      "date": "2026-02-27",
      "mid": 9.029073,
      "spread_pct": 0.077827,
      "gap": 2.069073,
      "log_depth": 13.584922,
      "z_gap": -1.335357,
      "z_spread": -0.79285,
      "z_liq": -1.613167,
      "emp": -1.924806,
      "emp_rolling": -1.329527,
      "emp_dfm": -1.914654,
      "emp_dfm_lo": -2.020146,
      "emp_dfm_hi": -1.809163,
      "prob_depr_14d": 0.65367,
      "prob_depr_30d": 0.769036,
      "alarm_mass_14d": 0.031012,
      "alarm_mass_30d": 0.107689
    },
    {
      "date": "2026-02-28",
      "mid": 9.276616,
      "spread_pct": 0.115924,
      "gap": 2.316616,
      "log_depth": 13.194153,
      "z_gap": -0.78576,
      "z_spread": -0.375189,
      "z_liq": -0.08885,
      "emp": -0.798809,
      "emp_rolling": 0.041107,
      "emp_dfm": -1.228463,
      "emp_dfm_lo": -1.333954,
      "emp_dfm_hi": -1.122971,
      "prob_depr_14d": 0.602486,
      "prob_depr_30d": 0.623878,
      "alarm_mass_14d": -0.030604,
      "alarm_mass_30d": -0.050629
    },
    {
      "date": "2026-03-01",
      "mid": 9.271607,
      "spread_pct": 0.085231,
      "gap": 2.311607,
      "log_depth": 13.085873,
      "z_gap": -0.796881,
      "z_spread": -0.265324,
      "z_liq": 0.738207,
      "emp": -0.469952,
      "emp_rolling": 0.511405,
      "emp_dfm": -1.235862,
      "emp_dfm_lo": -1.341353,
      "emp_dfm_hi": -1.130371,
      "prob_depr_14d": 0.645812,
      "prob_depr_30d": 0.666794,
      "alarm_mass_14d": 0.014006,
      "alarm_mass_30d": 0.000663
    },
    {
      "date": "2026-03-02",
      "mid": 9.182618,
      "spread_pct": 0.099847,
      "gap": 2.222618,
      "log_depth": 13.180548,
      "z_gap": -0.994455,
      "z_spread": -0.452306,
      "z_liq": -0.758026,
      "emp": -1.19855,
      "emp_rolling": -0.380703,
      "emp_dfm": -1.484802,
      "emp_dfm_lo": -1.590293,
      "emp_dfm_hi": -1.379311,
      "prob_depr_14d": 0.646116,
      "prob_depr_30d": 0.727379,
      "alarm_mass_14d": 0.016594,
      "alarm_mass_30d": 0.06732
    },
    {
      "date": "2026-03-03",
      "mid": 9.116385,
      "spread_pct": 0.068029,
      "gap": 2.156385,
      "log_depth": 13.464698,
      "z_gap": -1.141506,
      "z_spread": -0.952678,
      "z_liq": -0.479706,
      "emp": -1.552245,
      "emp_rolling": -0.858564,
      "emp_dfm": -1.673957,
      "emp_dfm_lo": -1.779448,
      "emp_dfm_hi": -1.568465,
      "prob_depr_14d": 0.544395,
      "prob_depr_30d": 0.532104,
      "alarm_mass_14d": -0.074739,
      "alarm_mass_30d": -0.110504
    },
    {
      "date": "2026-03-04",
      "mid": 9.110181,
      "spread_pct": 0.059905,
      "gap": 2.150181,
      "log_depth": 13.388497,
      "z_gap": -1.155282,
      "z_spread": -0.877804,
      "z_liq": -0.850533,
      "emp": -1.626204,
      "emp_rolling": -0.910549,
      "emp_dfm": -1.691923,
      "emp_dfm_lo": -1.797415,
      "emp_dfm_hi": -1.586432,
      "prob_depr_14d": 0.570486,
      "prob_depr_30d": 0.598359,
      "alarm_mass_14d": -0.03033,
      "alarm_mass_30d": -0.011029
    },
    {
      "date": "2026-03-05",
      "mid": 9.265755,
      "spread_pct": 0.057864,
      "gap": 2.305755,
      "log_depth": 13.187962,
      "z_gap": -0.809875,
      "z_spread": -0.758712,
      "z_liq": 1.184643,
      "emp": -0.678609,
      "emp_rolling": 0.302623,
      "emp_dfm": -1.259592,
      "emp_dfm_lo": -1.365083,
      "emp_dfm_hi": -1.1541,
      "prob_depr_14d": 0.498428,
      "prob_depr_30d": 0.369799,
      "alarm_mass_14d": -0.085135,
      "alarm_mass_30d": -0.206114
    },
    {
      "date": "2026-03-06",
      "mid": 9.386672,
      "spread_pct": 0.083537,
      "gap": 2.426672,
      "log_depth": 13.284725,
      "z_gap": -0.541413,
      "z_spread": -0.672949,
      "z_liq": -0.881216,
      "emp": -1.094577,
      "emp_rolling": -0.15417,
      "emp_dfm": -0.92431,
      "emp_dfm_lo": -1.029801,
      "emp_dfm_hi": -0.818818,
      "prob_depr_14d": 0.412165,
      "prob_depr_30d": 0.313136,
      "alarm_mass_14d": -0.146212,
      "alarm_mass_30d": -0.218252
    },
    {
      "date": "2026-03-07",
      "mid": 9.511586,
      "spread_pct": 0.080339,
      "gap": 2.551586,
      "log_depth": 13.504927,
      "z_gap": -0.264076,
      "z_spread": -0.45064,
      "z_liq": -0.63233,
      "emp": -0.682125,
      "emp_rolling": 0.41662,
      "emp_dfm": -0.574973,
      "emp_dfm_lo": -0.680464,
      "emp_dfm_hi": -0.469481,
      "prob_depr_14d": 0.385312,
      "prob_depr_30d": 0.26128,
      "alarm_mass_14d": -0.134898,
      "alarm_mass_30d": -0.209097
    },
    {
      "date": "2026-03-08",
      "mid": 9.518118,
      "spread_pct": 0.087426,
      "gap": 2.558118,
      "log_depth": 13.557677,
      "z_gap": -0.249573,
      "z_spread": -0.558026,
      "z_liq": -0.402477,
      "emp": -0.6745,
      "emp_rolling": 0.416124,
      "emp_dfm": -0.55552,
      "emp_dfm_lo": -0.661012,
      "emp_dfm_hi": -0.450029,
      "prob_depr_14d": 0.349663,
      "prob_depr_30d": 0.202338,
      "alarm_mass_14d": -0.133267,
      "alarm_mass_30d": -0.211019
    },
    {
      "date": "2026-03-09",
      "mid": 9.38349,
      "spread_pct": 0.083907,
      "gap": 2.42349,
      "log_depth": 13.664399,
      "z_gap": -0.548478,
      "z_spread": -0.769296,
      "z_liq": -1.238969,
      "emp": -1.278274,
      "emp_rolling": -0.358319,
      "emp_dfm": -0.929804,
      "emp_dfm_lo": -1.035295,
      "emp_dfm_hi": -0.824312,
      "prob_depr_14d": 0.382053,
      "prob_depr_30d": 0.278271,
      "alarm_mass_14d": -0.08259,
      "alarm_mass_30d": -0.107589
    },
    {
      "date": "2026-03-10",
      "mid": 9.234826,
      "spread_pct": 0.064457,
      "gap": 2.274826,
      "log_depth": 13.821719,
      "z_gap": -0.878542,
      "z_spread": -0.666334,
      "z_liq": -1.305029,
      "emp": -1.442951,
      "emp_rolling": -0.527754,
      "emp_dfm": -1.341453,
      "emp_dfm_lo": -1.446945,
      "emp_dfm_hi": -1.235962,
      "prob_depr_14d": 0.534084,
      "prob_depr_30d": 0.553343,
      "alarm_mass_14d": 0.078739,
      "alarm_mass_30d": 0.177833
    },
    {
      "date": "2026-03-11",
      "mid": 9.398008,
      "spread_pct": 0.07091,
      "gap": 2.438008,
      "log_depth": 13.853065,
      "z_gap": -0.516243,
      "z_spread": -0.52233,
      "z_liq": -0.199803,
      "emp": -0.759771,
      "emp_rolling": 0.508758,
      "emp_dfm": -0.891373,
      "emp_dfm_lo": -0.996864,
      "emp_dfm_hi": -0.785881,
      "prob_depr_14d": 0.456289,
      "prob_depr_30d": 0.359222,
      "alarm_mass_14d": -0.001396,
      "alarm_mass_30d": -0.022163
    },
    {
      "date": "2026-03-12",
      "mid": 9.445081,
      "spread_pct": 0.070646,
      "gap": 2.485081,
      "log_depth": 13.528034,
      "z_gap": -0.411733,
      "z_spread": -0.469845,
      "z_liq": 0.210556,
      "emp": -0.526337,
      "emp_rolling": 0.925334,
      "emp_dfm": -0.757614,
      "emp_dfm_lo": -0.863105,
      "emp_dfm_hi": -0.652123,
      "prob_depr_14d": 0.438272,
      "prob_depr_30d": 0.311515,
      "alarm_mass_14d": -0.016757,
      "alarm_mass_30d": -0.062565
    },
    {
      "date": "2026-03-13",
      "mid": 9.35971,
      "spread_pct": 0.062519,
      "gap": 2.39971,
      "log_depth": 13.424768,
      "z_gap": -0.601272,
      "z_spread": -0.705174,
      "z_liq": 0.306014,
      "emp": -0.782242,
      "emp_rolling": 0.525159,
      "emp_dfm": -0.994565,
      "emp_dfm_lo": -1.100056,
      "emp_dfm_hi": -0.889074,
      "prob_depr_14d": 0.432546,
      "prob_depr_30d": 0.297669,
      "alarm_mass_14d": -0.019851,
      "alarm_mass_30d": -0.068269
    },
    {
      "date": "2026-03-14",
      "mid": 9.419658,
      "spread_pct": 0.06503,
      "gap": 2.459658,
      "log_depth": 13.310448,
      "z_gap": -0.468177,
      "z_spread": -0.690266,
      "z_liq": 0.602636,
      "emp": -0.591923,
      "emp_rolling": 0.90773,
      "emp_dfm": -0.830275,
      "emp_dfm_lo": -0.935766,
      "emp_dfm_hi": -0.724783,
      "prob_depr_14d": 0.392039,
      "prob_depr_30d": 0.226586,
      "alarm_mass_14d": -0.049389,
      "alarm_mass_30d": -0.116397
    },
    {
      "date": "2026-03-15",
      "mid": 9.343139,
      "spread_pct": 0.069854,
      "gap": 2.383139,
      "log_depth": 13.398582,
      "z_gap": -0.638066,
      "z_spread": -0.767208,
      "z_liq": -0.388343,
      "emp": -1.067526,
      "emp_rolling": 0.194355,
      "emp_dfm": -1.042075,
      "emp_dfm_lo": -1.147567,
      "emp_dfm_hi": -0.936584,
      "prob_depr_14d": 0.420781,
      "prob_depr_30d": 0.30671,
      "alarm_mass_14d": -0.014032,
      "alarm_mass_30d": -0.023956
    },
    {
      "date": "2026-03-16",
      "mid": 9.382035,
      "spread_pct": 0.076952,
      "gap": 2.422035,
      "log_depth": 13.627145,
      "z_gap": -0.551708,
      "z_spread": -0.814441,
      "z_liq": -0.220119,
      "emp": -0.990957,
      "emp_rolling": 0.329307,
      "emp_dfm": -0.936457,
      "emp_dfm_lo": -1.041948,
      "emp_dfm_hi": -0.830965,
      "prob_depr_14d": 0.376908,
      "prob_depr_30d": 0.233149,
      "alarm_mass_14d": -0.059651,
      "alarm_mass_30d": -0.101163
    },
    {
      "date": "2026-03-17",
      "mid": 9.265531,
      "spread_pct": 0.054457,
      "gap": 2.305531,
      "log_depth": 13.684974,
      "z_gap": -0.810371,
      "z_spread": -0.995771,
      "z_liq": -1.041708,
      "emp": -1.543158,
      "emp_rolling": -0.617572,
      "emp_dfm": -1.25985,
      "emp_dfm_lo": -1.365341,
      "emp_dfm_hi": -1.154358,
      "prob_depr_14d": 0.405417,
      "prob_depr_30d": 0.307558,
      "alarm_mass_14d": -0.027473,
      "alarm_mass_30d": -0.021431
    },
    {
      "date": "2026-03-18",
      "mid": 9.287149,
      "spread_pct": 0.055195,
      "gap": 2.327149,
      "log_depth": 13.699953,
      "z_gap": -0.762374,
      "z_spread": -1.077068,
      "z_liq": -1.314007,
      "emp": -1.653711,
      "emp_rolling": -0.739162,
      "emp_dfm": -1.203412,
      "emp_dfm_lo": -1.308903,
      "emp_dfm_hi": -1.09792,
      "prob_depr_14d": 0.361788,
      "prob_depr_30d": 0.248759,
      "alarm_mass_14d": -0.068754,
      "alarm_mass_30d": -0.077743
    },
    {
      "date": "2026-03-19",
      "mid": 9.403607,
      "spread_pct": 0.055634,
      "gap": 2.443607,
      "log_depth": 13.715552,
      "z_gap": -0.503812,
      "z_spread": -0.662171,
      "z_liq": -0.116604,
      "emp": -0.822051,
      "emp_rolling": 0.830657,
      "emp_dfm": -0.876352,
      "emp_dfm_lo": -0.981843,
      "emp_dfm_hi": -0.77086,
      "prob_depr_14d": 0.40796,
      "prob_depr_30d": 0.275888,
      "alarm_mass_14d": -0.018677,
      "alarm_mass_30d": -0.045022
    },
    {
      "date": "2026-03-20",
      "mid": 9.300411,
      "spread_pct": 0.054686,
      "gap": 2.340411,
      "log_depth": 13.550258,
      "z_gap": -0.732929,
      "z_spread": -0.815712,
      "z_liq": -0.421845,
      "emp": -1.173347,
      "emp_rolling": 0.150048,
      "emp_dfm": -1.160788,
      "emp_dfm_lo": -1.26628,
      "emp_dfm_hi": -1.055297,
      "prob_depr_14d": 0.439326,
      "prob_depr_30d": 0.338832,
      "alarm_mass_14d": 0.021024,
      "alarm_mass_30d": 0.032157
    },
    {
      "date": "2026-03-21",
      "mid": 9.484671,
      "spread_pct": 0.053231,
      "gap": 2.524671,
      "log_depth": 13.297844,
      "z_gap": -0.323833,
      "z_spread": -0.922931,
      "z_liq": -0.005828,
      "emp": -0.850015,
      "emp_rolling": 0.994208,
      "emp_dfm": -0.654937,
      "emp_dfm_lo": -0.760429,
      "emp_dfm_hi": -0.549446,
      "prob_depr_14d": 0.274447,
      "prob_depr_30d": 0.108105,
      "alarm_mass_14d": -0.129071,
      "alarm_mass_30d": -0.172685
    },
    {
      "date": "2026-03-22",
      "mid": 9.420555,
      "spread_pct": 0.06019,
      "gap": 2.460555,
      "log_depth": 13.391412,
      "z_gap": -0.466185,
      "z_spread": -0.965264,
      "z_liq": -0.679755,
      "emp": -1.184021,
      "emp_rolling": 0.39138,
      "emp_dfm": -0.829618,
      "emp_dfm_lo": -0.935109,
      "emp_dfm_hi": -0.724127,
      "prob_depr_14d": 0.301813,
      "prob_depr_30d": 0.150348,
      "alarm_mass_14d": -0.082947,
      "alarm_mass_30d": -0.103076
    },
    {
      "date": "2026-03-23",
      "mid": 9.273948,
      "spread_pct": 0.044433,
      "gap": 2.313948,
      "log_depth": 13.584406,
      "z_gap": -0.791683,
      "z_spread": -1.206138,
      "z_liq": -1.114323,
      "emp": -1.699088,
      "emp_rolling": -0.757361,
      "emp_dfm": -1.238124,
      "emp_dfm_lo": -1.343616,
      "emp_dfm_hi": -1.132633,
      "prob_depr_14d": 0.335001,
      "prob_depr_30d": 0.20326,
      "alarm_mass_14d": -0.043259,
      "alarm_mass_30d": -0.040841
    },
    {
      "date": "2026-03-24",
      "mid": 9.362011,
      "spread_pct": 0.050618,
      "gap": 2.402011,
      "log_depth": 13.403364,
      "z_gap": -0.596165,
      "z_spread": -0.931498,
      "z_liq": -0.285203,
      "emp": -1.121218,
      "emp_rolling": 0.356117,
      "emp_dfm": -0.994236,
      "emp_dfm_lo": -1.099727,
      "emp_dfm_hi": -0.888744,
      "prob_depr_14d": 0.35637,
      "prob_depr_30d": 0.206682,
      "alarm_mass_14d": -0.018624,
      "alarm_mass_30d": -0.031014
    },
    {
      "date": "2026-03-25",
      "mid": 9.281259,
      "spread_pct": 0.039292,
      "gap": 2.321259,
      "log_depth": 13.794891,
      "z_gap": -0.775451,
      "z_spread": -1.163551,
      "z_liq": -0.97843,
      "emp": -1.616351,
      "emp_rolling": -0.610039,
      "emp_dfm": -1.218467,
      "emp_dfm_lo": -1.323958,
      "emp_dfm_hi": -1.112976,
      "prob_depr_14d": 0.342982,
      "prob_depr_30d": 0.209981,
      "alarm_mass_14d": -0.028422,
      "alarm_mass_30d": -0.024389
    },
    {
      "date": "2026-03-26",
      "mid": 9.262718,
      "spread_pct": 0.04815,
      "gap": 2.302718,
      "log_depth": 13.717086,
      "z_gap": -0.816616,
      "z_spread": -1.03635,
      "z_liq": -1.515634,
      "emp": -1.72437,
      "emp_rolling": -0.713803,
      "emp_dfm": -1.270335,
      "emp_dfm_lo": -1.375826,
      "emp_dfm_hi": -1.164843,
      "prob_depr_14d": 0.39144,
      "prob_depr_30d": 0.303672,
      "alarm_mass_14d": 0.023884,
      "alarm_mass_30d": 0.074133
    },
    {
      "date": "2026-03-27",
      "mid": 9.31296,
      "spread_pct": 0.038645,
      "gap": 2.35296,
      "log_depth": 13.663112,
      "z_gap": -0.705069,
      "z_spread": -1.313937,
      "z_liq": -1.182441,
      "emp": -1.738539,
      "emp_rolling": -0.771379,
      "emp_dfm": -1.134532,
      "emp_dfm_lo": -1.240024,
      "emp_dfm_hi": -1.029041,
      "prob_depr_14d": 0.277851,
      "prob_depr_30d": 0.134957,
      "alarm_mass_14d": -0.080468,
      "alarm_mass_30d": -0.083084
    },
    {
      "date": "2026-03-28",
      "mid": 9.315869,
      "spread_pct": 0.033391,
      "gap": 2.355869,
      "log_depth": 13.905194,
      "z_gap": -0.69861,
      "z_spread": -1.347183,
      "z_liq": -1.351429,
      "emp": -1.810461,
      "emp_rolling": -0.852173,
      "emp_dfm": -1.126118,
      "emp_dfm_lo": -1.23161,
      "emp_dfm_hi": -1.020627,
      "prob_depr_14d": 0.266376,
      "prob_depr_30d": 0.126308,
      "alarm_mass_14d": -0.08257,
      "alarm_mass_30d": -0.081516
    },
    {
      "date": "2026-03-29",
      "mid": 9.288838,
      "spread_pct": 0.042473,
      "gap": 2.328838,
      "log_depth": 13.925324,
      "z_gap": -0.758624,
      "z_spread": -1.116925,
      "z_liq": -1.176735,
      "emp": -1.635595,
      "emp_rolling": -0.549935,
      "emp_dfm": -1.198143,
      "emp_dfm_lo": -1.303635,
      "emp_dfm_hi": -1.092652,
      "prob_depr_14d": 0.34966,
      "prob_depr_30d": 0.22599,
      "alarm_mass_14d": 0.003461,
      "alarm_mass_30d": 0.020332
    },
    {
      "date": "2026-03-30",
      "mid": 9.308395,
      "spread_pct": 0.034035,
      "gap": 2.348395,
      "log_depth": 13.714455,
      "z_gap": -0.715204,
      "z_spread": -1.201529,
      "z_liq": -0.668577,
      "emp": -1.505833,
      "emp_rolling": -0.379014,
      "emp_dfm": -1.145011,
      "emp_dfm_lo": -1.250502,
      "emp_dfm_hi": -1.039519,
      "prob_depr_14d": 0.314692,
      "prob_depr_30d": 0.164554,
      "alarm_mass_14d": -0.026966,
      "alarm_mass_30d": -0.03532
    },
    {
      "date": "2026-03-31",
      "mid": 9.295878,
      "spread_pct": 0.051092,
      "gap": 2.335878,
      "log_depth": 13.615198,
      "z_gap": -0.742995,
      "z_spread": -0.859318,
      "z_liq": -0.122157,
      "emp": -1.115711,
      "emp_rolling": 0.286356,
      "emp_dfm": -1.175202,
      "emp_dfm_lo": -1.280693,
      "emp_dfm_hi": -1.06971,
      "prob_depr_14d": 0.431372,
      "prob_depr_30d": 0.312759,
      "alarm_mass_14d": 0.087313,
      "alarm_mass_30d": 0.110298
    },
    {
      "date": "2026-04-01",
      "mid": 9.251271,
      "spread_pct": 0.084977,
      "gap": 2.291271,
      "log_depth": 13.485421,
      "z_gap": -0.842032,
      "z_spread": -0.605609,
      "z_liq": -0.541362,
      "emp": -1.136947,
      "emp_rolling": 0.283576,
      "emp_dfm": -1.296323,
      "emp_dfm_lo": -1.401814,
      "emp_dfm_hi": -1.190832,
      "prob_depr_14d": 0.546252,
      "prob_depr_30d": 0.539819,
      "alarm_mass_14d": 0.186898,
      "alarm_mass_30d": 0.313937
    },
    {
      "date": "2026-04-02",
      "mid": 9.270427,
      "spread_pct": 0.074104,
      "gap": 2.310427,
      "log_depth": 13.718657,
      "z_gap": -0.7995,
      "z_spread": -0.615523,
      "z_liq": -0.276279,
      "emp": -1.032678,
      "emp_rolling": 0.458167,
      "emp_dfm": -1.244101,
      "emp_dfm_lo": -1.349592,
      "emp_dfm_hi": -1.13861,
      "prob_depr_14d": 0.529561,
      "prob_depr_30d": 0.495758,
      "alarm_mass_14d": 0.156467,
      "alarm_mass_30d": 0.247242
    },
    {
      "date": "2026-04-03",
      "mid": 9.268756,
      "spread_pct": 0.062963,
      "gap": 2.308756,
      "log_depth": 13.555601,
      "z_gap": -0.803211,
      "z_spread": -1.079549,
      "z_liq": -0.871602,
      "emp": -1.542816,
      "emp_rolling": -0.4738,
      "emp_dfm": -1.253646,
      "emp_dfm_lo": -1.359138,
      "emp_dfm_hi": -1.148155,
      "prob_depr_14d": 0.378284,
      "prob_depr_30d": 0.257644,
      "alarm_mass_14d": -0.000455,
      "alarm_mass_30d": 0.001703
    },
    {
      "date": "2026-04-04",
      "mid": 9.297138,
      "spread_pct": 0.070618,
      "gap": 2.337138,
      "log_depth": 13.037468,
      "z_gap": -0.740196,
      "z_spread": -1.029055,
      "z_liq": -0.276493,
      "emp": -1.279651,
      "emp_rolling": -0.046263,
      "emp_dfm": -1.174303,
      "emp_dfm_lo": -1.279795,
      "emp_dfm_hi": -1.068812,
      "prob_depr_14d": 0.376267,
      "prob_depr_30d": 0.233606,
      "alarm_mass_14d": -0.006613,
      "alarm_mass_30d": -0.025451
    }
  ]
}